crosstown_core/__init__.py
crosstown_core/__main__.py
crosstown_core/cli.py
crosstown_core/utils.py
crosstown_core/models/__init__.py
crosstown_core/models/alpine.py
crosstown_core/stubs/__init__.py
crosstown_core/stubs/alpine/__init__.py
crosstown_core/stubs/alpine/aiohttp.py
crosstown_core/stubs/alpine/aioquic.py
crosstown_core/stubs/alpine/argon_cffi.py
crosstown_core/stubs/alpine/astropy.py
crosstown_core/stubs/alpine/asyncpg.py
crosstown_core/stubs/alpine/bcrypt.py
crosstown_core/stubs/alpine/bjoern.py
crosstown_core/stubs/alpine/blis.py
crosstown_core/stubs/alpine/cchardet.py
crosstown_core/stubs/alpine/cffi.py
crosstown_core/stubs/alpine/cryptography.py
crosstown_core/stubs/alpine/cymem.py
crosstown_core/stubs/alpine/cython.py
crosstown_core/stubs/alpine/fastparquet.py
crosstown_core/stubs/alpine/gdal.py
crosstown_core/stubs/alpine/gensim.py
crosstown_core/stubs/alpine/gevent.py
crosstown_core/stubs/alpine/greenlet.py
crosstown_core/stubs/alpine/grpcio.py
crosstown_core/stubs/alpine/grpcio_tools.py
crosstown_core/stubs/alpine/h5py.py
crosstown_core/stubs/alpine/httptools.py
crosstown_core/stubs/alpine/immutables.py
crosstown_core/stubs/alpine/japronto.py
crosstown_core/stubs/alpine/kiwisolver.py
crosstown_core/stubs/alpine/lazy_object_proxy.py
crosstown_core/stubs/alpine/lxml.py
crosstown_core/stubs/alpine/markupsafe.py
crosstown_core/stubs/alpine/matplotlib.py
crosstown_core/stubs/alpine/meinheld.py
crosstown_core/stubs/alpine/msgpack.py
crosstown_core/stubs/alpine/msgpack_python.py
crosstown_core/stubs/alpine/multidict.py
crosstown_core/stubs/alpine/murmurhash.py
crosstown_core/stubs/alpine/numba.py
crosstown_core/stubs/alpine/numexpr.py
crosstown_core/stubs/alpine/numpy.py
crosstown_core/stubs/alpine/pandas.py
crosstown_core/stubs/alpine/pillow.py
crosstown_core/stubs/alpine/pillow_simd.py
crosstown_core/stubs/alpine/preshed.py
crosstown_core/stubs/alpine/protobuf.py
crosstown_core/stubs/alpine/psutil.py
crosstown_core/stubs/alpine/psycopg2.py
crosstown_core-2019.11.13.2044.dist-info/LICENSE
crosstown_core-2019.11.13.2044.dist-info/WHEEL
crosstown_core-2019.11.13.2044.dist-info/METADATA
crosstown_core-2019.11.13.2044.dist-info/RECORD
