Metadata-Version: 2.1
Name: crosstown-core
Version: 2019.11.13.2044
Summary: Faster, simpler, and slimmer container builds for Python
Home-page: https://docs.crosstown.dev
License: UNKNOWN
Author: Seth Michael Larson
Author-email: sethmichaellarson@gmail.com
Classifier: License :: OSI Approved :: GNU Lesser General Public License v3 or later (LGPLv3+)
Requires-Dist: attrs
Requires-Dist: click
Requires-Dist: packaging
Requires-Dist: requests
